app/__init__.py
app/cli.py
app/client.py
app/config.py
app/logging_config.py
app/main.py
app/monitoring.py
app/scalar.config.json
app/scalar_docs.py
app/settings.py
app/versioning.py
app/data/districts.json
app/data/districts.min.json
app/data/neighborhoods.json
app/data/neighborhoods.min.json
app/data/provinces.json
app/data/provinces.min.json
app/data/towns.json
app/data/towns.min.json
app/data/villages.json
app/data/villages.min.json
app/i18n/__init__.py
app/i18n/context.py
app/i18n/loader.py
app/i18n/negotiation.py
app/locales/__init__.py
app/locales/en.json
app/locales/tr.json
app/middleware/__init__.py
app/middleware/language.py
app/middleware/metrics.py
app/middleware/rate_limit.py
app/middleware/security.py
app/models/__init__.py
app/models/schemas.py
app/routers/__init__.py
app/routers/districts.py
app/routers/neighborhoods.py
app/routers/provinces.py
app/routers/towns.py
app/routers/villages.py
app/services/__init__.py
app/services/base_service.py
app/services/cache_service.py
app/services/data_loader.py
app/services/district_service.py
app/services/neighborhood_service.py
app/services/province_service.py
app/services/town_service.py
app/services/village_service.py
turkiye_api_py-1.1.1.dist-info/licenses/LICENSE
turkiye_api_py-1.1.1.dist-info/METADATA
turkiye_api_py-1.1.1.dist-info/WHEEL
turkiye_api_py-1.1.1.dist-info/entry_points.txt
turkiye_api_py-1.1.1.dist-info/top_level.txt
turkiye_api_py-1.1.1.dist-info/RECORD
