Metadata-Version: 2.4
Name: turkiye-api-py
Version: 1.1.1
Summary: Comprehensive REST API and Python SDK for Turkey's administrative divisions with demographic and geographical data
Author-email: Adem Kurtipek <gncharitaci@gmail.com>
Maintainer-email: Adem Kurtipek <gncharitaci@gmail.com>
License: MIT
Project-URL: Homepage, https://github.com/gencharitaci/turkiye-api-py
Project-URL: Documentation, https://github.com/gencharitaci/turkiye-api-py#readme
Project-URL: Repository, https://github.com/gencharitaci/turkiye-api-py
Project-URL: Issues, https://github.com/gencharitaci/turkiye-api-py/issues
Project-URL: Changelog, https://github.com/gencharitaci/turkiye-api-py/blob/master/docs/CHANGELOG.md
Keywords: türkiye,turkiye,turkiye-api,turkiye-api-py,api,fastapi,provinces,districts,administrative-divisions,geographic-data,demographic-data,rest-api,sdk
Classifier: Development Status :: 5 - Production/Stable
Classifier: Intended Audience :: Developers
Classifier: License :: OSI Approved :: MIT License
Classifier: Operating System :: OS Independent
Classifier: Programming Language :: Python :: 3
Classifier: Programming Language :: Python :: 3.8
Classifier: Programming Language :: Python :: 3.9
Classifier: Programming Language :: Python :: 3.10
Classifier: Programming Language :: Python :: 3.11
Classifier: Programming Language :: Python :: 3.12
Classifier: Programming Language :: Python :: 3.13
Classifier: Programming Language :: Python :: 3.14
Classifier: Framework :: FastAPI
Classifier: Topic :: Internet :: WWW/HTTP :: HTTP Servers
Classifier: Topic :: Software Development :: Libraries :: Python Modules
Classifier: Topic :: Scientific/Engineering :: GIS
Requires-Python: >=3.8
License-File: LICENSE
Requires-Dist: fastapi==0.122.0
Requires-Dist: uvicorn[standard]==0.38.0
Requires-Dist: pydantic==2.12.5
Requires-Dist: pydantic-settings==2.12.0
Requires-Dist: python-dotenv==1.2.1
Requires-Dist: markdown==3.10
Requires-Dist: python-frontmatter==1.1.0
Requires-Dist: pygments==2.19.2
Requires-Dist: python-json-logger==4.0.0
Requires-Dist: slowapi==0.1.9
Requires-Dist: prometheus-fastapi-instrumentator==7.1.0
Requires-Dist: httpx==0.28.1
Provides-Extra: server
Requires-Dist: gunicorn==23.0.0; extra == "server"
Requires-Dist: redis>=5.0.0; extra == "server"
Provides-Extra: dev
Requires-Dist: pytest>=7.4.0; extra == "dev"
Requires-Dist: pytest-cov>=4.1.0; extra == "dev"
Requires-Dist: pytest-asyncio>=0.21.0; extra == "dev"
Requires-Dist: black>=23.12.0; extra == "dev"
Requires-Dist: isort>=5.13.0; extra == "dev"
Requires-Dist: flake8>=7.0.0; extra == "dev"
Requires-Dist: mypy>=1.8.0; extra == "dev"
Requires-Dist: bandit>=1.7.6; extra == "dev"
Requires-Dist: pre-commit>=3.5.0; extra == "dev"
Provides-Extra: all
Requires-Dist: turkiye-api-py[dev,server]; extra == "all"
Dynamic: license-file
